<?xml version="1.1" encoding="UTF-8" standalone="no"?>
<databaseChangeLog xmlns="http://www.liquibase.org/xml/ns/dbchangelog" xmlns:ext="http://www.liquibase.org/xml/ns/dbchangelog-ext" xmlns:pro="http://www.liquibase.org/xml/ns/pro" xmlns:xsi="http://www.w3.org/2001/XMLSchema-instance" xsi:schemaLocation="http://www.liquibase.org/xml/ns/dbchangelog-ext http://www.liquibase.org/xml/ns/dbchangelog/dbchangelog-ext.xsd http://www.liquibase.org/xml/ns/pro http://www.liquibase.org/xml/ns/pro/liquibase-pro-4.1.xsd http://www.liquibase.org/xml/ns/dbchangelog http://www.liquibase.org/xml/ns/dbchangelog/dbchangelog-4.1.xsd">
    <changeSet author="leonardo.lira" id="202105041000-1">
        <loadData file="data/permissions/202105041000-permission_resource.csv"
                  relativeToChangelogFile="true"
                  schemaName="marfim"
                  separator=","
                  tableName="permission_resource">
            <column header="code"
                    name="code"
                    type="STRING"/>
            <column header="name"
                    name="name"
                    type="STRING"/>
        </loadData>
    </changeSet>
    <changeSet author="leonardo.lira" id="202105041000-2">
        <loadData file="data/permissions/202105041000-permission_level.csv"
                  relativeToChangelogFile="true"
                  schemaName="marfim"
                  separator=","
                  tableName="permission_level">
            <column header="code"
                    name="code"
                    type="STRING"/>
            <column header="name"
                    name="name"
                    type="STRING"/>
        </loadData>
    </changeSet>
    <changeSet author="leonardo.lira" id="202105041000-3">
        <loadData file="data/permissions/202105041000-permission.csv"
                  relativeToChangelogFile="true"
                  schemaName="marfim"
                  separator=","
                  tableName="permission">
            <column header="permission_resource_code"
                    name="permission_resource_code"
                    type="STRING"/>
            <column header="permission_level_code"
                    name="permission_level_code"
                    type="STRING"/>
        </loadData>
    </changeSet>

</databaseChangeLog>
